{"nodes": [{"id": "c_workspace_driver_model_repository_xgboost_spatial_corrector_1_model_json", "label": "model.json", "file_type": "code", "source_file": "C:\\workspace\\Driver\\model_repository\\xgboost_spatial_corrector\\1\\model.json", "source_location": "L1"}, {"id": "1_model_learner", "label": "learner", "file_type": "code", "source_file": "C:\\workspace\\Driver\\model_repository\\xgboost_spatial_corrector\\1\\model.json", "source_location": "L2"}, {"id": "1_model_learner_objective", "label": "objective", "file_type": "code", "source_file": "C:\\workspace\\Driver\\model_repository\\xgboost_spatial_corrector\\1\\model.json", "source_location": "L3"}, {"id": "1_model_objective_name", "label": "name", "file_type": "code", "source_file": "C:\\workspace\\Driver\\model_repository\\xgboost_spatial_corrector\\1\\model.json", "source_location": "L4"}, {"id": "1_model_learner_gradient_booster", "label": "gradient_booster", "file_type": "code", "source_file": "C:\\workspace\\Driver\\model_repository\\xgboost_spatial_corrector\\1\\model.json", "source_location": "L6"}, {"id": "1_model_gradient_booster_model", "label": "model", "file_type": "code", "source_file": "C:\\workspace\\Driver\\model_repository\\xgboost_spatial_corrector\\1\\model.json", "source_location": "L7"}, {"id": "1_model_model_gbtree_model_param", "label": "gbtree_model_param", "file_type": "code", "source_file": "C:\\workspace\\Driver\\model_repository\\xgboost_spatial_corrector\\1\\model.json", "source_location": "L8"}, {"id": "1_model_gbtree_model_param_num_trees", "label": "num_trees", "file_type": "code", "source_file": "C:\\workspace\\Driver\\model_repository\\xgboost_spatial_corrector\\1\\model.json", "source_location": "L9"}, {"id": "1_model_gbtree_model_param_size_leaf_vector", "label": "size_leaf_vector", "file_type": "code", "source_file": "C:\\workspace\\Driver\\model_repository\\xgboost_spatial_corrector\\1\\model.json", "source_location": "L10"}, {"id": "1_model_model_trees", "label": "trees", "file_type": "code", "source_file": "C:\\workspace\\Driver\\model_repository\\xgboost_spatial_corrector\\1\\model.json", "source_location": "L12"}, {"id": "1_model_version", "label": "version", "file_type": "code", "source_file": "C:\\workspace\\Driver\\model_repository\\xgboost_spatial_corrector\\1\\model.json", "source_location": "L34"}], "edges": [{"source": "c_workspace_driver_model_repository_xgboost_spatial_corrector_1_model_json", "target": "1_model_learner", "relation": "contains", "confidence": "EXTRACTED", "source_file": "C:\\workspace\\Driver\\model_repository\\xgboost_spatial_corrector\\1\\model.json", "source_location": "L2", "weight": 1.0}, {"source": "1_model_learner", "target": "1_model_learner_objective", "relation": "contains", "confidence": "EXTRACTED", "source_file": "C:\\workspace\\Driver\\model_repository\\xgboost_spatial_corrector\\1\\model.json", "source_location": "L3", "weight": 1.0}, {"source": "1_model_learner_objective", "target": "1_model_objective_name", "relation": "contains", "confidence": "EXTRACTED", "source_file": "C:\\workspace\\Driver\\model_repository\\xgboost_spatial_corrector\\1\\model.json", "source_location": "L4", "weight": 1.0}, {"source": "1_model_learner", "target": "1_model_learner_gradient_booster", "relation": "contains", "confidence": "EXTRACTED", "source_file": "C:\\workspace\\Driver\\model_repository\\xgboost_spatial_corrector\\1\\model.json", "source_location": "L6", "weight": 1.0}, {"source": "1_model_learner_gradient_booster", "target": "1_model_gradient_booster_model", "relation": "contains", "confidence": "EXTRACTED", "source_file": "C:\\workspace\\Driver\\model_repository\\xgboost_spatial_corrector\\1\\model.json", "source_location": "L7", "weight": 1.0}, {"source": "1_model_gradient_booster_model", "target": "1_model_model_gbtree_model_param", "relation": "contains", "confidence": "EXTRACTED", "source_file": "C:\\workspace\\Driver\\model_repository\\xgboost_spatial_corrector\\1\\model.json", "source_location": "L8", "weight": 1.0}, {"source": "1_model_model_gbtree_model_param", "target": "1_model_gbtree_model_param_num_trees", "relation": "contains", "confidence": "EXTRACTED", "source_file": "C:\\workspace\\Driver\\model_repository\\xgboost_spatial_corrector\\1\\model.json", "source_location": "L9", "weight": 1.0}, {"source": "1_model_model_gbtree_model_param", "target": "1_model_gbtree_model_param_size_leaf_vector", "relation": "contains", "confidence": "EXTRACTED", "source_file": "C:\\workspace\\Driver\\model_repository\\xgboost_spatial_corrector\\1\\model.json", "source_location": "L10", "weight": 1.0}, {"source": "1_model_gradient_booster_model", "target": "1_model_model_trees", "relation": "contains", "confidence": "EXTRACTED", "source_file": "C:\\workspace\\Driver\\model_repository\\xgboost_spatial_corrector\\1\\model.json", "source_location": "L12", "weight": 1.0}, {"source": "c_workspace_driver_model_repository_xgboost_spatial_corrector_1_model_json", "target": "1_model_version", "relation": "contains", "confidence": "EXTRACTED", "source_file": "C:\\workspace\\Driver\\model_repository\\xgboost_spatial_corrector\\1\\model.json", "source_location": "L34", "weight": 1.0}]}