{
  "project_info": {
    "project_number": "1016868477506",
    "project_id": "vahnly-platform",
    "storage_bucket": "vahnly-platform.firebasestorage.app"
  },
  "client": [
    {
      "client_info": {
        "mobilesdk_app_id": "1:1016868477506:android:ac85012fd450dd0f43abdb",
        "android_client_info": {
          "package_name": "com.vahnly.driver"
        }
      },
      "oauth_client": [
        {
          "client_id": "1016868477506-e8v36s2vuma8id60c17ijobjeg0ufuo9.apps.googleusercontent.com",
          "client_type": 1,
          "android_info": {
            "package_name": "com.vahnly.driver",
            "certificate_hash": "84140cd2bc41eefc805e9ae14f44e36c9934ff1b"
          }
        },
        {
          "client_id": "1016868477506-ql98dsuphlm7t1ftumqjj89rptsg9947.apps.googleusercontent.com",
          "client_type": 3
        }
      ],
      "api_key": [
        {
          "current_key": "AIzaSyBc5byg3MbbpSQHlHMAU3hdxfcevdNOYvM"
        }
      ],
      "services": {
        "appinvite_service": {
          "other_platform_oauth_client": [
            {
              "client_id": "1016868477506-ql98dsuphlm7t1ftumqjj89rptsg9947.apps.googleusercontent.com",
              "client_type": 3
            },
            {
              "client_id": "1016868477506-bh622jnm5n63k71otbmfcrt0greoqkku.apps.googleusercontent.com",
              "client_type": 2,
              "ios_info": {
                "bundle_id": "com.vahnly.rider"
              }
            }
          ]
        }
      }
    },
    {
      "client_info": {
        "mobilesdk_app_id": "1:1016868477506:android:2cb3e626b1fefb8343abdb",
        "android_client_info": {
          "package_name": "com.vahnly.rider"
        }
      },
      "oauth_client": [
        {
          "client_id": "1016868477506-kbu0bj2j2ejp73qn9e1a2v80v0vn25b2.apps.googleusercontent.com",
          "client_type": 1,
          "android_info": {
            "package_name": "com.vahnly.rider",
            "certificate_hash": "84140cd2bc41eefc805e9ae14f44e36c9934ff1b"
          }
        },
        {
          "client_id": "1016868477506-ql98dsuphlm7t1ftumqjj89rptsg9947.apps.googleusercontent.com",
          "client_type": 3
        }
      ],
      "api_key": [
        {
          "current_key": "AIzaSyBc5byg3MbbpSQHlHMAU3hdxfcevdNOYvM"
        }
      ],
      "services": {
        "appinvite_service": {
          "other_platform_oauth_client": [
            {
              "client_id": "1016868477506-ql98dsuphlm7t1ftumqjj89rptsg9947.apps.googleusercontent.com",
              "client_type": 3
            },
            {
              "client_id": "1016868477506-bh622jnm5n63k71otbmfcrt0greoqkku.apps.googleusercontent.com",
              "client_type": 2,
              "ios_info": {
                "bundle_id": "com.vahnly.rider"
              }
            }
          ]
        }
      }
    }
  ],
  "configuration_version": "1"
}
